{"frames":{"PA_1201":{"frame":{"x":0,"y":0,"w":128,"h":128},"sourceSize":{"w":128,"h":128},"spriteSourceSize":{"x":0,"y":0,"w":128,"h":128}},"PA_1202":{"frame":{"x":128,"y":0,"w":128,"h":128},"sourceSize":{"w":128,"h":128},"spriteSourceSize":{"x":0,"y":0,"w":128,"h":128}},"PA_1203":{"frame":{"x":256,"y":0,"w":128,"h":128},"sourceSize":{"w":128,"h":128},"spriteSourceSize":{"x":0,"y":0,"w":128,"h":128}},"PA_1204":{"frame":{"x":384,"y":0,"w":128,"h":128},"sourceSize":{"w":128,"h":128},"spriteSourceSize":{"x":0,"y":0,"w":128,"h":128}},"PA_1205":{"frame":{"x":512,"y":0,"w":128,"h":128},"sourceSize":{"w":128,"h":128},"spriteSourceSize":{"x":0,"y":0,"w":128,"h":128}},"PA_1206":{"frame":{"x":640,"y":0,"w":128,"h":128},"sourceSize":{"w":128,"h":128},"spriteSourceSize":{"x":0,"y":0,"w":128,"h":128}},"PA_1207":{"frame":{"x":768,"y":0,"w":128,"h":128},"sourceSize":{"w":128,"h":128},"spriteSourceSize":{"x":0,"y":0,"w":128,"h":128}},"PA_1208":{"frame":{"x":896,"y":0,"w":128,"h":128},"sourceSize":{"w":128,"h":128},"spriteSourceSize":{"x":0,"y":0,"w":128,"h":128}},"PA_1209":{"frame":{"x":1024,"y":0,"w":128,"h":128},"sourceSize":{"w":128,"h":128},"spriteSourceSize":{"x":0,"y":0,"w":128,"h":128}},"PA_1210":{"frame":{"x":1152,"y":0,"w":128,"h":128},"sourceSize":{"w":128,"h":128},"spriteSourceSize":{"x":0,"y":0,"w":128,"h":128}},"PA_1211":{"frame":{"x":1280,"y":0,"w":128,"h":128},"sourceSize":{"w":128,"h":128},"spriteSourceSize":{"x":0,"y":0,"w":128,"h":128}},"PA_1212":{"frame":{"x":1408,"y":0,"w":128,"h":128},"sourceSize":{"w":128,"h":128},"spriteSourceSize":{"x":0,"y":0,"w":128,"h":128}},"PA_1213":{"frame":{"x":1536,"y":0,"w":128,"h":128},"sourceSize":{"w":128,"h":128},"spriteSourceSize":{"x":0,"y":0,"w":128,"h":128}},"PA_1214":{"frame":{"x":1664,"y":0,"w":128,"h":128},"sourceSize":{"w":128,"h":128},"spriteSourceSize":{"x":0,"y":0,"w":128,"h":128}},"PA_1215":{"frame":{"x":1792,"y":0,"w":128,"h":128},"sourceSize":{"w":128,"h":128},"spriteSourceSize":{"x":0,"y":0,"w":128,"h":128}},"PA_1216":{"frame":{"x":1920,"y":0,"w":128,"h":128},"sourceSize":{"w":128,"h":128},"spriteSourceSize":{"x":0,"y":0,"w":128,"h":128}},"PA_1217":{"frame":{"x":2048,"y":0,"w":128,"h":128},"sourceSize":{"w":128,"h":128},"spriteSourceSize":{"x":0,"y":0,"w":128,"h":128}},"PA_1218":{"frame":{"x":2176,"y":0,"w":128,"h":128},"sourceSize":{"w":128,"h":128},"spriteSourceSize":{"x":0,"y":0,"w":128,"h":128}},"PA_1219":{"frame":{"x":2304,"y":0,"w":128,"h":128},"sourceSize":{"w":128,"h":128},"spriteSourceSize":{"x":0,"y":0,"w":128,"h":128}},"PA_1220":{"frame":{"x":2432,"y":0,"w":128,"h":128},"sourceSize":{"w":128,"h":128},"spriteSourceSize":{"x":0,"y":0,"w":128,"h":128}},"PA_1221":{"frame":{"x":0,"y":128,"w":128,"h":128},"sourceSize":{"w":128,"h":128},"spriteSourceSize":{"x":0,"y":0,"w":128,"h":128}},"PA_1222":{"frame":{"x":128,"y":128,"w":128,"h":128},"sourceSize":{"w":128,"h":128},"spriteSourceSize":{"x":0,"y":0,"w":128,"h":128}},"PA_1223":{"frame":{"x":256,"y":128,"w":128,"h":128},"sourceSize":{"w":128,"h":128},"spriteSourceSize":{"x":0,"y":0,"w":128,"h":128}},"PA_1224":{"frame":{"x":384,"y":128,"w":128,"h":128},"sourceSize":{"w":128,"h":128},"spriteSourceSize":{"x":0,"y":0,"w":128,"h":128}},"PA_1225":{"frame":{"x":512,"y":128,"w":128,"h":128},"sourceSize":{"w":128,"h":128},"spriteSourceSize":{"x":0,"y":0,"w":128,"h":128}},"PA_1226":{"frame":{"x":640,"y":128,"w":128,"h":128},"sourceSize":{"w":128,"h":128},"spriteSourceSize":{"x":0,"y":0,"w":128,"h":128}},"PA_1227":{"frame":{"x":768,"y":128,"w":128,"h":128},"sourceSize":{"w":128,"h":128},"spriteSourceSize":{"x":0,"y":0,"w":128,"h":128}},"PA_1228":{"frame":{"x":896,"y":128,"w":128,"h":128},"sourceSize":{"w":128,"h":128},"spriteSourceSize":{"x":0,"y":0,"w":128,"h":128}},"PA_1229":{"frame":{"x":1024,"y":128,"w":128,"h":128},"sourceSize":{"w":128,"h":128},"spriteSourceSize":{"x":0,"y":0,"w":128,"h":128}},"PA_1230":{"frame":{"x":1152,"y":128,"w":128,"h":128},"sourceSize":{"w":128,"h":128},"spriteSourceSize":{"x":0,"y":0,"w":128,"h":128}},"PA_1231":{"frame":{"x":1280,"y":128,"w":128,"h":128},"sourceSize":{"w":128,"h":128},"spriteSourceSize":{"x":0,"y":0,"w":128,"h":128}},"PA_1232":{"frame":{"x":1408,"y":128,"w":128,"h":128},"sourceSize":{"w":128,"h":128},"spriteSourceSize":{"x":0,"y":0,"w":128,"h":128}},"PA_1233":{"frame":{"x":1536,"y":128,"w":128,"h":128},"sourceSize":{"w":128,"h":128},"spriteSourceSize":{"x":0,"y":0,"w":128,"h":128}},"PA_1234":{"frame":{"x":1664,"y":128,"w":128,"h":128},"sourceSize":{"w":128,"h":128},"spriteSourceSize":{"x":0,"y":0,"w":128,"h":128}},"PA_1235":{"frame":{"x":1792,"y":128,"w":128,"h":128},"sourceSize":{"w":128,"h":128},"spriteSourceSize":{"x":0,"y":0,"w":128,"h":128}},"PA_1236":{"frame":{"x":1920,"y":128,"w":128,"h":128},"sourceSize":{"w":128,"h":128},"spriteSourceSize":{"x":0,"y":0,"w":128,"h":128}},"PA_1237":{"frame":{"x":2048,"y":128,"w":128,"h":128},"sourceSize":{"w":128,"h":128},"spriteSourceSize":{"x":0,"y":0,"w":128,"h":128}},"PA_1238":{"frame":{"x":2176,"y":128,"w":128,"h":128},"sourceSize":{"w":128,"h":128},"spriteSourceSize":{"x":0,"y":0,"w":128,"h":128}},"PA_1239":{"frame":{"x":2304,"y":128,"w":128,"h":128},"sourceSize":{"w":128,"h":128},"spriteSourceSize":{"x":0,"y":0,"w":128,"h":128}},"PA_1240":{"frame":{"x":2432,"y":128,"w":128,"h":128},"sourceSize":{"w":128,"h":128},"spriteSourceSize":{"x":0,"y":0,"w":128,"h":128}},"PA_1241":{"frame":{"x":0,"y":256,"w":128,"h":128},"sourceSize":{"w":128,"h":128},"spriteSourceSize":{"x":0,"y":0,"w":128,"h":128}},"PA_1242":{"frame":{"x":128,"y":256,"w":128,"h":128},"sourceSize":{"w":128,"h":128},"spriteSourceSize":{"x":0,"y":0,"w":128,"h":128}},"PA_1243":{"frame":{"x":256,"y":256,"w":128,"h":128},"sourceSize":{"w":128,"h":128},"spriteSourceSize":{"x":0,"y":0,"w":128,"h":128}},"PA_1244":{"frame":{"x":384,"y":256,"w":128,"h":128},"sourceSize":{"w":128,"h":128},"spriteSourceSize":{"x":0,"y":0,"w":128,"h":128}},"PA_1245":{"frame":{"x":512,"y":256,"w":128,"h":128},"sourceSize":{"w":128,"h":128},"spriteSourceSize":{"x":0,"y":0,"w":128,"h":128}},"PA_1246":{"frame":{"x":640,"y":256,"w":128,"h":128},"sourceSize":{"w":128,"h":128},"spriteSourceSize":{"x":0,"y":0,"w":128,"h":128}},"PA_1247":{"frame":{"x":768,"y":256,"w":128,"h":128},"sourceSize":{"w":128,"h":128},"spriteSourceSize":{"x":0,"y":0,"w":128,"h":128}},"PA_1248":{"frame":{"x":896,"y":256,"w":128,"h":128},"sourceSize":{"w":128,"h":128},"spriteSourceSize":{"x":0,"y":0,"w":128,"h":128}},"PA_1249":{"frame":{"x":1024,"y":256,"w":128,"h":128},"sourceSize":{"w":128,"h":128},"spriteSourceSize":{"x":0,"y":0,"w":128,"h":128}},"PA_1250":{"frame":{"x":1152,"y":256,"w":128,"h":128},"sourceSize":{"w":128,"h":128},"spriteSourceSize":{"x":0,"y":0,"w":128,"h":128}},"PA_1251":{"frame":{"x":1280,"y":256,"w":128,"h":128},"sourceSize":{"w":128,"h":128},"spriteSourceSize":{"x":0,"y":0,"w":128,"h":128}},"PA_1252":{"frame":{"x":1408,"y":256,"w":128,"h":128},"sourceSize":{"w":128,"h":128},"spriteSourceSize":{"x":0,"y":0,"w":128,"h":128}},"PA_1253":{"frame":{"x":1536,"y":256,"w":128,"h":128},"sourceSize":{"w":128,"h":128},"spriteSourceSize":{"x":0,"y":0,"w":128,"h":128}},"PA_1254":{"frame":{"x":1664,"y":256,"w":128,"h":128},"sourceSize":{"w":128,"h":128},"spriteSourceSize":{"x":0,"y":0,"w":128,"h":128}},"PA_1255":{"frame":{"x":1792,"y":256,"w":128,"h":128},"sourceSize":{"w":128,"h":128},"spriteSourceSize":{"x":0,"y":0,"w":128,"h":128}},"PA_1256":{"frame":{"x":1920,"y":256,"w":128,"h":128},"sourceSize":{"w":128,"h":128},"spriteSourceSize":{"x":0,"y":0,"w":128,"h":128}},"PA_1257":{"frame":{"x":2048,"y":256,"w":128,"h":128},"sourceSize":{"w":128,"h":128},"spriteSourceSize":{"x":0,"y":0,"w":128,"h":128}},"PA_1258":{"frame":{"x":2176,"y":256,"w":128,"h":128},"sourceSize":{"w":128,"h":128},"spriteSourceSize":{"x":0,"y":0,"w":128,"h":128}},"PA_1259":{"frame":{"x":2304,"y":256,"w":128,"h":128},"sourceSize":{"w":128,"h":128},"spriteSourceSize":{"x":0,"y":0,"w":128,"h":128}},"PA_1260":{"frame":{"x":2432,"y":256,"w":128,"h":128},"sourceSize":{"w":128,"h":128},"spriteSourceSize":{"x":0,"y":0,"w":128,"h":128}},"PA_1261":{"frame":{"x":0,"y":384,"w":128,"h":128},"sourceSize":{"w":128,"h":128},"spriteSourceSize":{"x":0,"y":0,"w":128,"h":128}},"PA_1262":{"frame":{"x":128,"y":384,"w":128,"h":128},"sourceSize":{"w":128,"h":128},"spriteSourceSize":{"x":0,"y":0,"w":128,"h":128}},"PA_1263":{"frame":{"x":256,"y":384,"w":128,"h":128},"sourceSize":{"w":128,"h":128},"spriteSourceSize":{"x":0,"y":0,"w":128,"h":128}},"PA_1264":{"frame":{"x":384,"y":384,"w":128,"h":128},"sourceSize":{"w":128,"h":128},"spriteSourceSize":{"x":0,"y":0,"w":128,"h":128}},"PA_1265":{"frame":{"x":512,"y":384,"w":128,"h":128},"sourceSize":{"w":128,"h":128},"spriteSourceSize":{"x":0,"y":0,"w":128,"h":128}},"PA_1266":{"frame":{"x":640,"y":384,"w":128,"h":128},"sourceSize":{"w":128,"h":128},"spriteSourceSize":{"x":0,"y":0,"w":128,"h":128}},"PA_1267":{"frame":{"x":768,"y":384,"w":128,"h":128},"sourceSize":{"w":128,"h":128},"spriteSourceSize":{"x":0,"y":0,"w":128,"h":128}},"PA_1268":{"frame":{"x":896,"y":384,"w":128,"h":128},"sourceSize":{"w":128,"h":128},"spriteSourceSize":{"x":0,"y":0,"w":128,"h":128}},"PA_1269":{"frame":{"x":1024,"y":384,"w":128,"h":128},"sourceSize":{"w":128,"h":128},"spriteSourceSize":{"x":0,"y":0,"w":128,"h":128}},"PA_1270":{"frame":{"x":1152,"y":384,"w":128,"h":128},"sourceSize":{"w":128,"h":128},"spriteSourceSize":{"x":0,"y":0,"w":128,"h":128}},"PA_1271":{"frame":{"x":1280,"y":384,"w":128,"h":128},"sourceSize":{"w":128,"h":128},"spriteSourceSize":{"x":0,"y":0,"w":128,"h":128}},"PA_1272":{"frame":{"x":1408,"y":384,"w":128,"h":128},"sourceSize":{"w":128,"h":128},"spriteSourceSize":{"x":0,"y":0,"w":128,"h":128}},"PA_1273":{"frame":{"x":1536,"y":384,"w":128,"h":128},"sourceSize":{"w":128,"h":128},"spriteSourceSize":{"x":0,"y":0,"w":128,"h":128}},"PA_1274":{"frame":{"x":1664,"y":384,"w":128,"h":128},"sourceSize":{"w":128,"h":128},"spriteSourceSize":{"x":0,"y":0,"w":128,"h":128}},"PA_1275":{"frame":{"x":1792,"y":384,"w":128,"h":128},"sourceSize":{"w":128,"h":128},"spriteSourceSize":{"x":0,"y":0,"w":128,"h":128}},"PA_1276":{"frame":{"x":1920,"y":384,"w":128,"h":128},"sourceSize":{"w":128,"h":128},"spriteSourceSize":{"x":0,"y":0,"w":128,"h":128}},"PA_1277":{"frame":{"x":2048,"y":384,"w":128,"h":128},"sourceSize":{"w":128,"h":128},"spriteSourceSize":{"x":0,"y":0,"w":128,"h":128}},"PA_1278":{"frame":{"x":2176,"y":384,"w":128,"h":128},"sourceSize":{"w":128,"h":128},"spriteSourceSize":{"x":0,"y":0,"w":128,"h":128}},"PA_1279":{"frame":{"x":2304,"y":384,"w":128,"h":128},"sourceSize":{"w":128,"h":128},"spriteSourceSize":{"x":0,"y":0,"w":128,"h":128}},"PA_1280":{"frame":{"x":2432,"y":384,"w":128,"h":128},"sourceSize":{"w":128,"h":128},"spriteSourceSize":{"x":0,"y":0,"w":128,"h":128}},"PA_1281":{"frame":{"x":0,"y":512,"w":128,"h":128},"sourceSize":{"w":128,"h":128},"spriteSourceSize":{"x":0,"y":0,"w":128,"h":128}},"PA_1282":{"frame":{"x":128,"y":512,"w":128,"h":128},"sourceSize":{"w":128,"h":128},"spriteSourceSize":{"x":0,"y":0,"w":128,"h":128}},"PA_1283":{"frame":{"x":256,"y":512,"w":128,"h":128},"sourceSize":{"w":128,"h":128},"spriteSourceSize":{"x":0,"y":0,"w":128,"h":128}},"PA_1284":{"frame":{"x":384,"y":512,"w":128,"h":128},"sourceSize":{"w":128,"h":128},"spriteSourceSize":{"x":0,"y":0,"w":128,"h":128}},"PA_1285":{"frame":{"x":512,"y":512,"w":128,"h":128},"sourceSize":{"w":128,"h":128},"spriteSourceSize":{"x":0,"y":0,"w":128,"h":128}},"PA_1286":{"frame":{"x":640,"y":512,"w":128,"h":128},"sourceSize":{"w":128,"h":128},"spriteSourceSize":{"x":0,"y":0,"w":128,"h":128}},"PA_1287":{"frame":{"x":768,"y":512,"w":128,"h":128},"sourceSize":{"w":128,"h":128},"spriteSourceSize":{"x":0,"y":0,"w":128,"h":128}},"PA_1288":{"frame":{"x":896,"y":512,"w":128,"h":128},"sourceSize":{"w":128,"h":128},"spriteSourceSize":{"x":0,"y":0,"w":128,"h":128}},"PA_1289":{"frame":{"x":1024,"y":512,"w":128,"h":128},"sourceSize":{"w":128,"h":128},"spriteSourceSize":{"x":0,"y":0,"w":128,"h":128}},"PA_1290":{"frame":{"x":1152,"y":512,"w":128,"h":128},"sourceSize":{"w":128,"h":128},"spriteSourceSize":{"x":0,"y":0,"w":128,"h":128}},"PA_1291":{"frame":{"x":1280,"y":512,"w":128,"h":128},"sourceSize":{"w":128,"h":128},"spriteSourceSize":{"x":0,"y":0,"w":128,"h":128}},"PA_1292":{"frame":{"x":1408,"y":512,"w":128,"h":128},"sourceSize":{"w":128,"h":128},"spriteSourceSize":{"x":0,"y":0,"w":128,"h":128}},"PA_1293":{"frame":{"x":1536,"y":512,"w":128,"h":128},"sourceSize":{"w":128,"h":128},"spriteSourceSize":{"x":0,"y":0,"w":128,"h":128}},"PA_1294":{"frame":{"x":1664,"y":512,"w":128,"h":128},"sourceSize":{"w":128,"h":128},"spriteSourceSize":{"x":0,"y":0,"w":128,"h":128}},"PA_1295":{"frame":{"x":1792,"y":512,"w":128,"h":128},"sourceSize":{"w":128,"h":128},"spriteSourceSize":{"x":0,"y":0,"w":128,"h":128}},"PA_1296":{"frame":{"x":1920,"y":512,"w":128,"h":128},"sourceSize":{"w":128,"h":128},"spriteSourceSize":{"x":0,"y":0,"w":128,"h":128}},"PA_1297":{"frame":{"x":2048,"y":512,"w":128,"h":128},"sourceSize":{"w":128,"h":128},"spriteSourceSize":{"x":0,"y":0,"w":128,"h":128}},"PA_1298":{"frame":{"x":2176,"y":512,"w":128,"h":128},"sourceSize":{"w":128,"h":128},"spriteSourceSize":{"x":0,"y":0,"w":128,"h":128}},"PA_1299":{"frame":{"x":2304,"y":512,"w":128,"h":128},"sourceSize":{"w":128,"h":128},"spriteSourceSize":{"x":0,"y":0,"w":128,"h":128}},"PA_1300":{"frame":{"x":2432,"y":512,"w":128,"h":128},"sourceSize":{"w":128,"h":128},"spriteSourceSize":{"x":0,"y":0,"w":128,"h":128}},"PA_1301":{"frame":{"x":0,"y":640,"w":128,"h":128},"sourceSize":{"w":128,"h":128},"spriteSourceSize":{"x":0,"y":0,"w":128,"h":128}},"PA_1302":{"frame":{"x":128,"y":640,"w":128,"h":128},"sourceSize":{"w":128,"h":128},"spriteSourceSize":{"x":0,"y":0,"w":128,"h":128}},"PA_1303":{"frame":{"x":256,"y":640,"w":128,"h":128},"sourceSize":{"w":128,"h":128},"spriteSourceSize":{"x":0,"y":0,"w":128,"h":128}},"PA_1304":{"frame":{"x":384,"y":640,"w":128,"h":128},"sourceSize":{"w":128,"h":128},"spriteSourceSize":{"x":0,"y":0,"w":128,"h":128}},"PA_1305":{"frame":{"x":512,"y":640,"w":128,"h":128},"sourceSize":{"w":128,"h":128},"spriteSourceSize":{"x":0,"y":0,"w":128,"h":128}},"PA_1306":{"frame":{"x":640,"y":640,"w":128,"h":128},"sourceSize":{"w":128,"h":128},"spriteSourceSize":{"x":0,"y":0,"w":128,"h":128}},"PA_1307":{"frame":{"x":768,"y":640,"w":128,"h":128},"sourceSize":{"w":128,"h":128},"spriteSourceSize":{"x":0,"y":0,"w":128,"h":128}},"PA_1308":{"frame":{"x":896,"y":640,"w":128,"h":128},"sourceSize":{"w":128,"h":128},"spriteSourceSize":{"x":0,"y":0,"w":128,"h":128}},"PA_1309":{"frame":{"x":1024,"y":640,"w":128,"h":128},"sourceSize":{"w":128,"h":128},"spriteSourceSize":{"x":0,"y":0,"w":128,"h":128}},"PA_1310":{"frame":{"x":1152,"y":640,"w":128,"h":128},"sourceSize":{"w":128,"h":128},"spriteSourceSize":{"x":0,"y":0,"w":128,"h":128}},"PA_1311":{"frame":{"x":1280,"y":640,"w":128,"h":128},"sourceSize":{"w":128,"h":128},"spriteSourceSize":{"x":0,"y":0,"w":128,"h":128}},"PA_1312":{"frame":{"x":1408,"y":640,"w":128,"h":128},"sourceSize":{"w":128,"h":128},"spriteSourceSize":{"x":0,"y":0,"w":128,"h":128}},"PA_1313":{"frame":{"x":1536,"y":640,"w":128,"h":128},"sourceSize":{"w":128,"h":128},"spriteSourceSize":{"x":0,"y":0,"w":128,"h":128}},"PA_1314":{"frame":{"x":1664,"y":640,"w":128,"h":128},"sourceSize":{"w":128,"h":128},"spriteSourceSize":{"x":0,"y":0,"w":128,"h":128}},"PA_1315":{"frame":{"x":1792,"y":640,"w":128,"h":128},"sourceSize":{"w":128,"h":128},"spriteSourceSize":{"x":0,"y":0,"w":128,"h":128}},"PA_1316":{"frame":{"x":1920,"y":640,"w":128,"h":128},"sourceSize":{"w":128,"h":128},"spriteSourceSize":{"x":0,"y":0,"w":128,"h":128}},"PA_1317":{"frame":{"x":2048,"y":640,"w":128,"h":128},"sourceSize":{"w":128,"h":128},"spriteSourceSize":{"x":0,"y":0,"w":128,"h":128}},"PA_1318":{"frame":{"x":2176,"y":640,"w":128,"h":128},"sourceSize":{"w":128,"h":128},"spriteSourceSize":{"x":0,"y":0,"w":128,"h":128}},"PA_1319":{"frame":{"x":2304,"y":640,"w":128,"h":128},"sourceSize":{"w":128,"h":128},"spriteSourceSize":{"x":0,"y":0,"w":128,"h":128}},"PA_1320":{"frame":{"x":2432,"y":640,"w":128,"h":128},"sourceSize":{"w":128,"h":128},"spriteSourceSize":{"x":0,"y":0,"w":128,"h":128}},"PA_1321":{"frame":{"x":0,"y":768,"w":128,"h":128},"sourceSize":{"w":128,"h":128},"spriteSourceSize":{"x":0,"y":0,"w":128,"h":128}},"PA_1322":{"frame":{"x":128,"y":768,"w":128,"h":128},"sourceSize":{"w":128,"h":128},"spriteSourceSize":{"x":0,"y":0,"w":128,"h":128}},"PA_1323":{"frame":{"x":256,"y":768,"w":128,"h":128},"sourceSize":{"w":128,"h":128},"spriteSourceSize":{"x":0,"y":0,"w":128,"h":128}},"PA_1324":{"frame":{"x":384,"y":768,"w":128,"h":128},"sourceSize":{"w":128,"h":128},"spriteSourceSize":{"x":0,"y":0,"w":128,"h":128}},"PA_1325":{"frame":{"x":512,"y":768,"w":128,"h":128},"sourceSize":{"w":128,"h":128},"spriteSourceSize":{"x":0,"y":0,"w":128,"h":128}},"PA_1326":{"frame":{"x":640,"y":768,"w":128,"h":128},"sourceSize":{"w":128,"h":128},"spriteSourceSize":{"x":0,"y":0,"w":128,"h":128}},"PA_1327":{"frame":{"x":768,"y":768,"w":128,"h":128},"sourceSize":{"w":128,"h":128},"spriteSourceSize":{"x":0,"y":0,"w":128,"h":128}},"PA_1328":{"frame":{"x":896,"y":768,"w":128,"h":128},"sourceSize":{"w":128,"h":128},"spriteSourceSize":{"x":0,"y":0,"w":128,"h":128}},"PA_1329":{"frame":{"x":1024,"y":768,"w":128,"h":128},"sourceSize":{"w":128,"h":128},"spriteSourceSize":{"x":0,"y":0,"w":128,"h":128}},"PA_1330":{"frame":{"x":1152,"y":768,"w":128,"h":128},"sourceSize":{"w":128,"h":128},"spriteSourceSize":{"x":0,"y":0,"w":128,"h":128}},"PA_1331":{"frame":{"x":1280,"y":768,"w":128,"h":128},"sourceSize":{"w":128,"h":128},"spriteSourceSize":{"x":0,"y":0,"w":128,"h":128}},"PA_1332":{"frame":{"x":1408,"y":768,"w":128,"h":128},"sourceSize":{"w":128,"h":128},"spriteSourceSize":{"x":0,"y":0,"w":128,"h":128}},"PA_1333":{"frame":{"x":1536,"y":768,"w":128,"h":128},"sourceSize":{"w":128,"h":128},"spriteSourceSize":{"x":0,"y":0,"w":128,"h":128}},"PA_1334":{"frame":{"x":1664,"y":768,"w":128,"h":128},"sourceSize":{"w":128,"h":128},"spriteSourceSize":{"x":0,"y":0,"w":128,"h":128}},"PA_1335":{"frame":{"x":1792,"y":768,"w":128,"h":128},"sourceSize":{"w":128,"h":128},"spriteSourceSize":{"x":0,"y":0,"w":128,"h":128}},"PA_1336":{"frame":{"x":1920,"y":768,"w":128,"h":128},"sourceSize":{"w":128,"h":128},"spriteSourceSize":{"x":0,"y":0,"w":128,"h":128}},"PA_1337":{"frame":{"x":2048,"y":768,"w":128,"h":128},"sourceSize":{"w":128,"h":128},"spriteSourceSize":{"x":0,"y":0,"w":128,"h":128}},"PA_1338":{"frame":{"x":2176,"y":768,"w":128,"h":128},"sourceSize":{"w":128,"h":128},"spriteSourceSize":{"x":0,"y":0,"w":128,"h":128}},"PA_1339":{"frame":{"x":2304,"y":768,"w":128,"h":128},"sourceSize":{"w":128,"h":128},"spriteSourceSize":{"x":0,"y":0,"w":128,"h":128}},"PA_1340":{"frame":{"x":2432,"y":768,"w":128,"h":128},"sourceSize":{"w":128,"h":128},"spriteSourceSize":{"x":0,"y":0,"w":128,"h":128}},"PA_1341":{"frame":{"x":0,"y":896,"w":128,"h":128},"sourceSize":{"w":128,"h":128},"spriteSourceSize":{"x":0,"y":0,"w":128,"h":128}},"PA_1342":{"frame":{"x":128,"y":896,"w":128,"h":128},"sourceSize":{"w":128,"h":128},"spriteSourceSize":{"x":0,"y":0,"w":128,"h":128}},"PA_1343":{"frame":{"x":256,"y":896,"w":128,"h":128},"sourceSize":{"w":128,"h":128},"spriteSourceSize":{"x":0,"y":0,"w":128,"h":128}},"PA_1344":{"frame":{"x":384,"y":896,"w":128,"h":128},"sourceSize":{"w":128,"h":128},"spriteSourceSize":{"x":0,"y":0,"w":128,"h":128}},"PA_1345":{"frame":{"x":512,"y":896,"w":128,"h":128},"sourceSize":{"w":128,"h":128},"spriteSourceSize":{"x":0,"y":0,"w":128,"h":128}},"PA_1346":{"frame":{"x":640,"y":896,"w":128,"h":128},"sourceSize":{"w":128,"h":128},"spriteSourceSize":{"x":0,"y":0,"w":128,"h":128}},"PA_1347":{"frame":{"x":768,"y":896,"w":128,"h":128},"sourceSize":{"w":128,"h":128},"spriteSourceSize":{"x":0,"y":0,"w":128,"h":128}},"PA_1348":{"frame":{"x":896,"y":896,"w":128,"h":128},"sourceSize":{"w":128,"h":128},"spriteSourceSize":{"x":0,"y":0,"w":128,"h":128}},"PA_1349":{"frame":{"x":1024,"y":896,"w":128,"h":128},"sourceSize":{"w":128,"h":128},"spriteSourceSize":{"x":0,"y":0,"w":128,"h":128}},"PA_1350":{"frame":{"x":1152,"y":896,"w":128,"h":128},"sourceSize":{"w":128,"h":128},"spriteSourceSize":{"x":0,"y":0,"w":128,"h":128}},"PA_1351":{"frame":{"x":1280,"y":896,"w":128,"h":128},"sourceSize":{"w":128,"h":128},"spriteSourceSize":{"x":0,"y":0,"w":128,"h":128}},"PA_1352":{"frame":{"x":1408,"y":896,"w":128,"h":128},"sourceSize":{"w":128,"h":128},"spriteSourceSize":{"x":0,"y":0,"w":128,"h":128}},"PA_1353":{"frame":{"x":1536,"y":896,"w":128,"h":128},"sourceSize":{"w":128,"h":128},"spriteSourceSize":{"x":0,"y":0,"w":128,"h":128}},"PA_1354":{"frame":{"x":1664,"y":896,"w":128,"h":128},"sourceSize":{"w":128,"h":128},"spriteSourceSize":{"x":0,"y":0,"w":128,"h":128}},"PA_1355":{"frame":{"x":1792,"y":896,"w":128,"h":128},"sourceSize":{"w":128,"h":128},"spriteSourceSize":{"x":0,"y":0,"w":128,"h":128}},"PA_1356":{"frame":{"x":1920,"y":896,"w":128,"h":128},"sourceSize":{"w":128,"h":128},"spriteSourceSize":{"x":0,"y":0,"w":128,"h":128}},"PA_1357":{"frame":{"x":2048,"y":896,"w":128,"h":128},"sourceSize":{"w":128,"h":128},"spriteSourceSize":{"x":0,"y":0,"w":128,"h":128}},"PA_1358":{"frame":{"x":2176,"y":896,"w":128,"h":128},"sourceSize":{"w":128,"h":128},"spriteSourceSize":{"x":0,"y":0,"w":128,"h":128}},"PA_1359":{"frame":{"x":2304,"y":896,"w":128,"h":128},"sourceSize":{"w":128,"h":128},"spriteSourceSize":{"x":0,"y":0,"w":128,"h":128}},"PA_1360":{"frame":{"x":2432,"y":896,"w":128,"h":128},"sourceSize":{"w":128,"h":128},"spriteSourceSize":{"x":0,"y":0,"w":128,"h":128}},"PA_1361":{"frame":{"x":0,"y":1024,"w":128,"h":128},"sourceSize":{"w":128,"h":128},"spriteSourceSize":{"x":0,"y":0,"w":128,"h":128}},"PA_1362":{"frame":{"x":128,"y":1024,"w":128,"h":128},"sourceSize":{"w":128,"h":128},"spriteSourceSize":{"x":0,"y":0,"w":128,"h":128}},"PA_1363":{"frame":{"x":256,"y":1024,"w":128,"h":128},"sourceSize":{"w":128,"h":128},"spriteSourceSize":{"x":0,"y":0,"w":128,"h":128}},"PA_1364":{"frame":{"x":384,"y":1024,"w":128,"h":128},"sourceSize":{"w":128,"h":128},"spriteSourceSize":{"x":0,"y":0,"w":128,"h":128}},"PA_1365":{"frame":{"x":512,"y":1024,"w":128,"h":128},"sourceSize":{"w":128,"h":128},"spriteSourceSize":{"x":0,"y":0,"w":128,"h":128}},"PA_1366":{"frame":{"x":640,"y":1024,"w":128,"h":128},"sourceSize":{"w":128,"h":128},"spriteSourceSize":{"x":0,"y":0,"w":128,"h":128}},"PA_1367":{"frame":{"x":768,"y":1024,"w":128,"h":128},"sourceSize":{"w":128,"h":128},"spriteSourceSize":{"x":0,"y":0,"w":128,"h":128}},"PA_1368":{"frame":{"x":896,"y":1024,"w":128,"h":128},"sourceSize":{"w":128,"h":128},"spriteSourceSize":{"x":0,"y":0,"w":128,"h":128}},"PA_1369":{"frame":{"x":1024,"y":1024,"w":128,"h":128},"sourceSize":{"w":128,"h":128},"spriteSourceSize":{"x":0,"y":0,"w":128,"h":128}},"PA_1370":{"frame":{"x":1152,"y":1024,"w":128,"h":128},"sourceSize":{"w":128,"h":128},"spriteSourceSize":{"x":0,"y":0,"w":128,"h":128}},"PA_1371":{"frame":{"x":1280,"y":1024,"w":128,"h":128},"sourceSize":{"w":128,"h":128},"spriteSourceSize":{"x":0,"y":0,"w":128,"h":128}},"PA_1372":{"frame":{"x":1408,"y":1024,"w":128,"h":128},"sourceSize":{"w":128,"h":128},"spriteSourceSize":{"x":0,"y":0,"w":128,"h":128}},"PA_1373":{"frame":{"x":1536,"y":1024,"w":128,"h":128},"sourceSize":{"w":128,"h":128},"spriteSourceSize":{"x":0,"y":0,"w":128,"h":128}},"PA_1374":{"frame":{"x":1664,"y":1024,"w":128,"h":128},"sourceSize":{"w":128,"h":128},"spriteSourceSize":{"x":0,"y":0,"w":128,"h":128}},"PA_1375":{"frame":{"x":1792,"y":1024,"w":128,"h":128},"sourceSize":{"w":128,"h":128},"spriteSourceSize":{"x":0,"y":0,"w":128,"h":128}},"PA_1376":{"frame":{"x":1920,"y":1024,"w":128,"h":128},"sourceSize":{"w":128,"h":128},"spriteSourceSize":{"x":0,"y":0,"w":128,"h":128}},"PA_1377":{"frame":{"x":2048,"y":1024,"w":128,"h":128},"sourceSize":{"w":128,"h":128},"spriteSourceSize":{"x":0,"y":0,"w":128,"h":128}},"PA_1378":{"frame":{"x":2176,"y":1024,"w":128,"h":128},"sourceSize":{"w":128,"h":128},"spriteSourceSize":{"x":0,"y":0,"w":128,"h":128}},"PA_1379":{"frame":{"x":2304,"y":1024,"w":128,"h":128},"sourceSize":{"w":128,"h":128},"spriteSourceSize":{"x":0,"y":0,"w":128,"h":128}},"PA_1380":{"frame":{"x":2432,"y":1024,"w":128,"h":128},"sourceSize":{"w":128,"h":128},"spriteSourceSize":{"x":0,"y":0,"w":128,"h":128}},"PA_1381":{"frame":{"x":0,"y":1152,"w":128,"h":128},"sourceSize":{"w":128,"h":128},"spriteSourceSize":{"x":0,"y":0,"w":128,"h":128}},"PA_1382":{"frame":{"x":128,"y":1152,"w":128,"h":128},"sourceSize":{"w":128,"h":128},"spriteSourceSize":{"x":0,"y":0,"w":128,"h":128}},"PA_1383":{"frame":{"x":256,"y":1152,"w":128,"h":128},"sourceSize":{"w":128,"h":128},"spriteSourceSize":{"x":0,"y":0,"w":128,"h":128}},"PA_1384":{"frame":{"x":384,"y":1152,"w":128,"h":128},"sourceSize":{"w":128,"h":128},"spriteSourceSize":{"x":0,"y":0,"w":128,"h":128}},"PA_1385":{"frame":{"x":512,"y":1152,"w":128,"h":128},"sourceSize":{"w":128,"h":128},"spriteSourceSize":{"x":0,"y":0,"w":128,"h":128}},"PA_1386":{"frame":{"x":640,"y":1152,"w":128,"h":128},"sourceSize":{"w":128,"h":128},"spriteSourceSize":{"x":0,"y":0,"w":128,"h":128}},"PA_1387":{"frame":{"x":768,"y":1152,"w":128,"h":128},"sourceSize":{"w":128,"h":128},"spriteSourceSize":{"x":0,"y":0,"w":128,"h":128}},"PA_1388":{"frame":{"x":896,"y":1152,"w":128,"h":128},"sourceSize":{"w":128,"h":128},"spriteSourceSize":{"x":0,"y":0,"w":128,"h":128}},"PA_1389":{"frame":{"x":1024,"y":1152,"w":128,"h":128},"sourceSize":{"w":128,"h":128},"spriteSourceSize":{"x":0,"y":0,"w":128,"h":128}},"PA_1390":{"frame":{"x":1152,"y":1152,"w":128,"h":128},"sourceSize":{"w":128,"h":128},"spriteSourceSize":{"x":0,"y":0,"w":128,"h":128}},"PA_1391":{"frame":{"x":1280,"y":1152,"w":128,"h":128},"sourceSize":{"w":128,"h":128},"spriteSourceSize":{"x":0,"y":0,"w":128,"h":128}},"PA_1392":{"frame":{"x":1408,"y":1152,"w":128,"h":128},"sourceSize":{"w":128,"h":128},"spriteSourceSize":{"x":0,"y":0,"w":128,"h":128}},"PA_1393":{"frame":{"x":1536,"y":1152,"w":128,"h":128},"sourceSize":{"w":128,"h":128},"spriteSourceSize":{"x":0,"y":0,"w":128,"h":128}},"PA_1394":{"frame":{"x":1664,"y":1152,"w":128,"h":128},"sourceSize":{"w":128,"h":128},"spriteSourceSize":{"x":0,"y":0,"w":128,"h":128}},"PA_1395":{"frame":{"x":1792,"y":1152,"w":128,"h":128},"sourceSize":{"w":128,"h":128},"spriteSourceSize":{"x":0,"y":0,"w":128,"h":128}},"PA_1396":{"frame":{"x":1920,"y":1152,"w":128,"h":128},"sourceSize":{"w":128,"h":128},"spriteSourceSize":{"x":0,"y":0,"w":128,"h":128}},"PA_1397":{"frame":{"x":2048,"y":1152,"w":128,"h":128},"sourceSize":{"w":128,"h":128},"spriteSourceSize":{"x":0,"y":0,"w":128,"h":128}},"PA_1398":{"frame":{"x":2176,"y":1152,"w":128,"h":128},"sourceSize":{"w":128,"h":128},"spriteSourceSize":{"x":0,"y":0,"w":128,"h":128}},"PA_1399":{"frame":{"x":2304,"y":1152,"w":128,"h":128},"sourceSize":{"w":128,"h":128},"spriteSourceSize":{"x":0,"y":0,"w":128,"h":128}},"PA_1400":{"frame":{"x":2432,"y":1152,"w":128,"h":128},"sourceSize":{"w":128,"h":128},"spriteSourceSize":{"x":0,"y":0,"w":128,"h":128}},"PA_1401":{"frame":{"x":0,"y":1280,"w":128,"h":128},"sourceSize":{"w":128,"h":128},"spriteSourceSize":{"x":0,"y":0,"w":128,"h":128}},"PA_1402":{"frame":{"x":128,"y":1280,"w":128,"h":128},"sourceSize":{"w":128,"h":128},"spriteSourceSize":{"x":0,"y":0,"w":128,"h":128}},"PA_1403":{"frame":{"x":256,"y":1280,"w":128,"h":128},"sourceSize":{"w":128,"h":128},"spriteSourceSize":{"x":0,"y":0,"w":128,"h":128}},"PA_1404":{"frame":{"x":384,"y":1280,"w":128,"h":128},"sourceSize":{"w":128,"h":128},"spriteSourceSize":{"x":0,"y":0,"w":128,"h":128}},"PA_1405":{"frame":{"x":512,"y":1280,"w":128,"h":128},"sourceSize":{"w":128,"h":128},"spriteSourceSize":{"x":0,"y":0,"w":128,"h":128}},"PA_1406":{"frame":{"x":640,"y":1280,"w":128,"h":128},"sourceSize":{"w":128,"h":128},"spriteSourceSize":{"x":0,"y":0,"w":128,"h":128}},"PA_1407":{"frame":{"x":768,"y":1280,"w":128,"h":128},"sourceSize":{"w":128,"h":128},"spriteSourceSize":{"x":0,"y":0,"w":128,"h":128}},"PA_1408":{"frame":{"x":896,"y":1280,"w":128,"h":128},"sourceSize":{"w":128,"h":128},"spriteSourceSize":{"x":0,"y":0,"w":128,"h":128}},"PA_1409":{"frame":{"x":1024,"y":1280,"w":128,"h":128},"sourceSize":{"w":128,"h":128},"spriteSourceSize":{"x":0,"y":0,"w":128,"h":128}},"PA_1410":{"frame":{"x":1152,"y":1280,"w":128,"h":128},"sourceSize":{"w":128,"h":128},"spriteSourceSize":{"x":0,"y":0,"w":128,"h":128}},"PA_1411":{"frame":{"x":1280,"y":1280,"w":128,"h":128},"sourceSize":{"w":128,"h":128},"spriteSourceSize":{"x":0,"y":0,"w":128,"h":128}},"PA_1412":{"frame":{"x":1408,"y":1280,"w":128,"h":128},"sourceSize":{"w":128,"h":128},"spriteSourceSize":{"x":0,"y":0,"w":128,"h":128}},"PA_1413":{"frame":{"x":1536,"y":1280,"w":128,"h":128},"sourceSize":{"w":128,"h":128},"spriteSourceSize":{"x":0,"y":0,"w":128,"h":128}},"PA_1414":{"frame":{"x":1664,"y":1280,"w":128,"h":128},"sourceSize":{"w":128,"h":128},"spriteSourceSize":{"x":0,"y":0,"w":128,"h":128}},"PA_1415":{"frame":{"x":1792,"y":1280,"w":128,"h":128},"sourceSize":{"w":128,"h":128},"spriteSourceSize":{"x":0,"y":0,"w":128,"h":128}},"PA_1416":{"frame":{"x":1920,"y":1280,"w":128,"h":128},"sourceSize":{"w":128,"h":128},"spriteSourceSize":{"x":0,"y":0,"w":128,"h":128}},"PA_1417":{"frame":{"x":2048,"y":1280,"w":128,"h":128},"sourceSize":{"w":128,"h":128},"spriteSourceSize":{"x":0,"y":0,"w":128,"h":128}},"PA_1418":{"frame":{"x":2176,"y":1280,"w":128,"h":128},"sourceSize":{"w":128,"h":128},"spriteSourceSize":{"x":0,"y":0,"w":128,"h":128}},"PA_1419":{"frame":{"x":2304,"y":1280,"w":128,"h":128},"sourceSize":{"w":128,"h":128},"spriteSourceSize":{"x":0,"y":0,"w":128,"h":128}},"PA_1420":{"frame":{"x":2432,"y":1280,"w":128,"h":128},"sourceSize":{"w":128,"h":128},"spriteSourceSize":{"x":0,"y":0,"w":128,"h":128}},"PA_1421":{"frame":{"x":0,"y":1408,"w":128,"h":128},"sourceSize":{"w":128,"h":128},"spriteSourceSize":{"x":0,"y":0,"w":128,"h":128}},"PA_1422":{"frame":{"x":128,"y":1408,"w":128,"h":128},"sourceSize":{"w":128,"h":128},"spriteSourceSize":{"x":0,"y":0,"w":128,"h":128}},"PA_1423":{"frame":{"x":256,"y":1408,"w":128,"h":128},"sourceSize":{"w":128,"h":128},"spriteSourceSize":{"x":0,"y":0,"w":128,"h":128}},"PA_1424":{"frame":{"x":384,"y":1408,"w":128,"h":128},"sourceSize":{"w":128,"h":128},"spriteSourceSize":{"x":0,"y":0,"w":128,"h":128}},"PA_1425":{"frame":{"x":512,"y":1408,"w":128,"h":128},"sourceSize":{"w":128,"h":128},"spriteSourceSize":{"x":0,"y":0,"w":128,"h":128}},"PA_1426":{"frame":{"x":640,"y":1408,"w":128,"h":128},"sourceSize":{"w":128,"h":128},"spriteSourceSize":{"x":0,"y":0,"w":128,"h":128}},"PA_1427":{"frame":{"x":768,"y":1408,"w":128,"h":128},"sourceSize":{"w":128,"h":128},"spriteSourceSize":{"x":0,"y":0,"w":128,"h":128}},"PA_1428":{"frame":{"x":896,"y":1408,"w":128,"h":128},"sourceSize":{"w":128,"h":128},"spriteSourceSize":{"x":0,"y":0,"w":128,"h":128}},"PA_1429":{"frame":{"x":1024,"y":1408,"w":128,"h":128},"sourceSize":{"w":128,"h":128},"spriteSourceSize":{"x":0,"y":0,"w":128,"h":128}},"PA_1430":{"frame":{"x":1152,"y":1408,"w":128,"h":128},"sourceSize":{"w":128,"h":128},"spriteSourceSize":{"x":0,"y":0,"w":128,"h":128}},"PA_1431":{"frame":{"x":1280,"y":1408,"w":128,"h":128},"sourceSize":{"w":128,"h":128},"spriteSourceSize":{"x":0,"y":0,"w":128,"h":128}},"PA_1432":{"frame":{"x":1408,"y":1408,"w":128,"h":128},"sourceSize":{"w":128,"h":128},"spriteSourceSize":{"x":0,"y":0,"w":128,"h":128}},"PA_1433":{"frame":{"x":1536,"y":1408,"w":128,"h":128},"sourceSize":{"w":128,"h":128},"spriteSourceSize":{"x":0,"y":0,"w":128,"h":128}},"PA_1434":{"frame":{"x":1664,"y":1408,"w":128,"h":128},"sourceSize":{"w":128,"h":128},"spriteSourceSize":{"x":0,"y":0,"w":128,"h":128}},"PA_1435":{"frame":{"x":1792,"y":1408,"w":128,"h":128},"sourceSize":{"w":128,"h":128},"spriteSourceSize":{"x":0,"y":0,"w":128,"h":128}},"PA_1436":{"frame":{"x":1920,"y":1408,"w":128,"h":128},"sourceSize":{"w":128,"h":128},"spriteSourceSize":{"x":0,"y":0,"w":128,"h":128}},"PA_1437":{"frame":{"x":2048,"y":1408,"w":128,"h":128},"sourceSize":{"w":128,"h":128},"spriteSourceSize":{"x":0,"y":0,"w":128,"h":128}},"PA_1438":{"frame":{"x":2176,"y":1408,"w":128,"h":128},"sourceSize":{"w":128,"h":128},"spriteSourceSize":{"x":0,"y":0,"w":128,"h":128}},"PA_1439":{"frame":{"x":2304,"y":1408,"w":128,"h":128},"sourceSize":{"w":128,"h":128},"spriteSourceSize":{"x":0,"y":0,"w":128,"h":128}},"PA_1440":{"frame":{"x":2432,"y":1408,"w":128,"h":128},"sourceSize":{"w":128,"h":128},"spriteSourceSize":{"x":0,"y":0,"w":128,"h":128}},"PA_1441":{"frame":{"x":0,"y":1536,"w":128,"h":128},"sourceSize":{"w":128,"h":128},"spriteSourceSize":{"x":0,"y":0,"w":128,"h":128}},"PA_1442":{"frame":{"x":128,"y":1536,"w":128,"h":128},"sourceSize":{"w":128,"h":128},"spriteSourceSize":{"x":0,"y":0,"w":128,"h":128}},"PA_1443":{"frame":{"x":256,"y":1536,"w":128,"h":128},"sourceSize":{"w":128,"h":128},"spriteSourceSize":{"x":0,"y":0,"w":128,"h":128}},"PA_1444":{"frame":{"x":384,"y":1536,"w":128,"h":128},"sourceSize":{"w":128,"h":128},"spriteSourceSize":{"x":0,"y":0,"w":128,"h":128}},"PA_1445":{"frame":{"x":512,"y":1536,"w":128,"h":128},"sourceSize":{"w":128,"h":128},"spriteSourceSize":{"x":0,"y":0,"w":128,"h":128}},"PA_1446":{"frame":{"x":640,"y":1536,"w":128,"h":128},"sourceSize":{"w":128,"h":128},"spriteSourceSize":{"x":0,"y":0,"w":128,"h":128}},"PA_1447":{"frame":{"x":768,"y":1536,"w":128,"h":128},"sourceSize":{"w":128,"h":128},"spriteSourceSize":{"x":0,"y":0,"w":128,"h":128}},"PA_1448":{"frame":{"x":896,"y":1536,"w":128,"h":128},"sourceSize":{"w":128,"h":128},"spriteSourceSize":{"x":0,"y":0,"w":128,"h":128}},"PA_1449":{"frame":{"x":1024,"y":1536,"w":128,"h":128},"sourceSize":{"w":128,"h":128},"spriteSourceSize":{"x":0,"y":0,"w":128,"h":128}},"PA_1450":{"frame":{"x":1152,"y":1536,"w":128,"h":128},"sourceSize":{"w":128,"h":128},"spriteSourceSize":{"x":0,"y":0,"w":128,"h":128}},"PA_1451":{"frame":{"x":1280,"y":1536,"w":128,"h":128},"sourceSize":{"w":128,"h":128},"spriteSourceSize":{"x":0,"y":0,"w":128,"h":128}},"PA_1452":{"frame":{"x":1408,"y":1536,"w":128,"h":128},"sourceSize":{"w":128,"h":128},"spriteSourceSize":{"x":0,"y":0,"w":128,"h":128}},"PA_1453":{"frame":{"x":1536,"y":1536,"w":128,"h":128},"sourceSize":{"w":128,"h":128},"spriteSourceSize":{"x":0,"y":0,"w":128,"h":128}},"PA_1454":{"frame":{"x":1664,"y":1536,"w":128,"h":128},"sourceSize":{"w":128,"h":128},"spriteSourceSize":{"x":0,"y":0,"w":128,"h":128}},"PA_1455":{"frame":{"x":1792,"y":1536,"w":128,"h":128},"sourceSize":{"w":128,"h":128},"spriteSourceSize":{"x":0,"y":0,"w":128,"h":128}},"PA_1456":{"frame":{"x":1920,"y":1536,"w":128,"h":128},"sourceSize":{"w":128,"h":128},"spriteSourceSize":{"x":0,"y":0,"w":128,"h":128}},"PA_1457":{"frame":{"x":2048,"y":1536,"w":128,"h":128},"sourceSize":{"w":128,"h":128},"spriteSourceSize":{"x":0,"y":0,"w":128,"h":128}},"PA_1458":{"frame":{"x":2176,"y":1536,"w":128,"h":128},"sourceSize":{"w":128,"h":128},"spriteSourceSize":{"x":0,"y":0,"w":128,"h":128}},"PA_1459":{"frame":{"x":2304,"y":1536,"w":128,"h":128},"sourceSize":{"w":128,"h":128},"spriteSourceSize":{"x":0,"y":0,"w":128,"h":128}},"PA_1460":{"frame":{"x":2432,"y":1536,"w":128,"h":128},"sourceSize":{"w":128,"h":128},"spriteSourceSize":{"x":0,"y":0,"w":128,"h":128}},"PA_1461":{"frame":{"x":0,"y":1664,"w":128,"h":128},"sourceSize":{"w":128,"h":128},"spriteSourceSize":{"x":0,"y":0,"w":128,"h":128}},"PA_1462":{"frame":{"x":128,"y":1664,"w":128,"h":128},"sourceSize":{"w":128,"h":128},"spriteSourceSize":{"x":0,"y":0,"w":128,"h":128}},"PA_1463":{"frame":{"x":256,"y":1664,"w":128,"h":128},"sourceSize":{"w":128,"h":128},"spriteSourceSize":{"x":0,"y":0,"w":128,"h":128}},"PA_1464":{"frame":{"x":384,"y":1664,"w":128,"h":128},"sourceSize":{"w":128,"h":128},"spriteSourceSize":{"x":0,"y":0,"w":128,"h":128}},"PA_1465":{"frame":{"x":512,"y":1664,"w":128,"h":128},"sourceSize":{"w":128,"h":128},"spriteSourceSize":{"x":0,"y":0,"w":128,"h":128}},"PA_1466":{"frame":{"x":640,"y":1664,"w":128,"h":128},"sourceSize":{"w":128,"h":128},"spriteSourceSize":{"x":0,"y":0,"w":128,"h":128}},"PA_1467":{"frame":{"x":768,"y":1664,"w":128,"h":128},"sourceSize":{"w":128,"h":128},"spriteSourceSize":{"x":0,"y":0,"w":128,"h":128}},"PA_1468":{"frame":{"x":896,"y":1664,"w":128,"h":128},"sourceSize":{"w":128,"h":128},"spriteSourceSize":{"x":0,"y":0,"w":128,"h":128}},"PA_1469":{"frame":{"x":1024,"y":1664,"w":128,"h":128},"sourceSize":{"w":128,"h":128},"spriteSourceSize":{"x":0,"y":0,"w":128,"h":128}},"PA_1470":{"frame":{"x":1152,"y":1664,"w":128,"h":128},"sourceSize":{"w":128,"h":128},"spriteSourceSize":{"x":0,"y":0,"w":128,"h":128}},"PA_1471":{"frame":{"x":1280,"y":1664,"w":128,"h":128},"sourceSize":{"w":128,"h":128},"spriteSourceSize":{"x":0,"y":0,"w":128,"h":128}},"PA_1472":{"frame":{"x":1408,"y":1664,"w":128,"h":128},"sourceSize":{"w":128,"h":128},"spriteSourceSize":{"x":0,"y":0,"w":128,"h":128}},"PA_1473":{"frame":{"x":1536,"y":1664,"w":128,"h":128},"sourceSize":{"w":128,"h":128},"spriteSourceSize":{"x":0,"y":0,"w":128,"h":128}},"PA_1474":{"frame":{"x":1664,"y":1664,"w":128,"h":128},"sourceSize":{"w":128,"h":128},"spriteSourceSize":{"x":0,"y":0,"w":128,"h":128}},"PA_1475":{"frame":{"x":1792,"y":1664,"w":128,"h":128},"sourceSize":{"w":128,"h":128},"spriteSourceSize":{"x":0,"y":0,"w":128,"h":128}},"PA_1476":{"frame":{"x":1920,"y":1664,"w":128,"h":128},"sourceSize":{"w":128,"h":128},"spriteSourceSize":{"x":0,"y":0,"w":128,"h":128}},"PA_1477":{"frame":{"x":2048,"y":1664,"w":128,"h":128},"sourceSize":{"w":128,"h":128},"spriteSourceSize":{"x":0,"y":0,"w":128,"h":128}},"PA_1478":{"frame":{"x":2176,"y":1664,"w":128,"h":128},"sourceSize":{"w":128,"h":128},"spriteSourceSize":{"x":0,"y":0,"w":128,"h":128}},"PA_1479":{"frame":{"x":2304,"y":1664,"w":128,"h":128},"sourceSize":{"w":128,"h":128},"spriteSourceSize":{"x":0,"y":0,"w":128,"h":128}},"PA_1480":{"frame":{"x":2432,"y":1664,"w":128,"h":128},"sourceSize":{"w":128,"h":128},"spriteSourceSize":{"x":0,"y":0,"w":128,"h":128}},"PA_1481":{"frame":{"x":0,"y":1792,"w":128,"h":128},"sourceSize":{"w":128,"h":128},"spriteSourceSize":{"x":0,"y":0,"w":128,"h":128}},"PA_1482":{"frame":{"x":128,"y":1792,"w":128,"h":128},"sourceSize":{"w":128,"h":128},"spriteSourceSize":{"x":0,"y":0,"w":128,"h":128}},"PA_1483":{"frame":{"x":256,"y":1792,"w":128,"h":128},"sourceSize":{"w":128,"h":128},"spriteSourceSize":{"x":0,"y":0,"w":128,"h":128}},"PA_1484":{"frame":{"x":384,"y":1792,"w":128,"h":128},"sourceSize":{"w":128,"h":128},"spriteSourceSize":{"x":0,"y":0,"w":128,"h":128}},"PA_1485":{"frame":{"x":512,"y":1792,"w":128,"h":128},"sourceSize":{"w":128,"h":128},"spriteSourceSize":{"x":0,"y":0,"w":128,"h":128}},"PA_1486":{"frame":{"x":640,"y":1792,"w":128,"h":128},"sourceSize":{"w":128,"h":128},"spriteSourceSize":{"x":0,"y":0,"w":128,"h":128}},"PA_1487":{"frame":{"x":768,"y":1792,"w":128,"h":128},"sourceSize":{"w":128,"h":128},"spriteSourceSize":{"x":0,"y":0,"w":128,"h":128}},"PA_1488":{"frame":{"x":896,"y":1792,"w":128,"h":128},"sourceSize":{"w":128,"h":128},"spriteSourceSize":{"x":0,"y":0,"w":128,"h":128}},"PA_1489":{"frame":{"x":1024,"y":1792,"w":128,"h":128},"sourceSize":{"w":128,"h":128},"spriteSourceSize":{"x":0,"y":0,"w":128,"h":128}},"PA_1490":{"frame":{"x":1152,"y":1792,"w":128,"h":128},"sourceSize":{"w":128,"h":128},"spriteSourceSize":{"x":0,"y":0,"w":128,"h":128}},"PA_1491":{"frame":{"x":1280,"y":1792,"w":128,"h":128},"sourceSize":{"w":128,"h":128},"spriteSourceSize":{"x":0,"y":0,"w":128,"h":128}},"PA_1492":{"frame":{"x":1408,"y":1792,"w":128,"h":128},"sourceSize":{"w":128,"h":128},"spriteSourceSize":{"x":0,"y":0,"w":128,"h":128}},"PA_1493":{"frame":{"x":1536,"y":1792,"w":128,"h":128},"sourceSize":{"w":128,"h":128},"spriteSourceSize":{"x":0,"y":0,"w":128,"h":128}},"PA_1494":{"frame":{"x":1664,"y":1792,"w":128,"h":128},"sourceSize":{"w":128,"h":128},"spriteSourceSize":{"x":0,"y":0,"w":128,"h":128}},"PA_1495":{"frame":{"x":1792,"y":1792,"w":128,"h":128},"sourceSize":{"w":128,"h":128},"spriteSourceSize":{"x":0,"y":0,"w":128,"h":128}},"PA_1496":{"frame":{"x":1920,"y":1792,"w":128,"h":128},"sourceSize":{"w":128,"h":128},"spriteSourceSize":{"x":0,"y":0,"w":128,"h":128}},"PA_1497":{"frame":{"x":2048,"y":1792,"w":128,"h":128},"sourceSize":{"w":128,"h":128},"spriteSourceSize":{"x":0,"y":0,"w":128,"h":128}},"PA_1498":{"frame":{"x":2176,"y":1792,"w":128,"h":128},"sourceSize":{"w":128,"h":128},"spriteSourceSize":{"x":0,"y":0,"w":128,"h":128}},"PA_1499":{"frame":{"x":2304,"y":1792,"w":128,"h":128},"sourceSize":{"w":128,"h":128},"spriteSourceSize":{"x":0,"y":0,"w":128,"h":128}},"PA_1500":{"frame":{"x":2432,"y":1792,"w":128,"h":128},"sourceSize":{"w":128,"h":128},"spriteSourceSize":{"x":0,"y":0,"w":128,"h":128}},"PA_1501":{"frame":{"x":0,"y":1920,"w":128,"h":128},"sourceSize":{"w":128,"h":128},"spriteSourceSize":{"x":0,"y":0,"w":128,"h":128}},"PA_1502":{"frame":{"x":128,"y":1920,"w":128,"h":128},"sourceSize":{"w":128,"h":128},"spriteSourceSize":{"x":0,"y":0,"w":128,"h":128}},"PA_1503":{"frame":{"x":256,"y":1920,"w":128,"h":128},"sourceSize":{"w":128,"h":128},"spriteSourceSize":{"x":0,"y":0,"w":128,"h":128}},"PA_1504":{"frame":{"x":384,"y":1920,"w":128,"h":128},"sourceSize":{"w":128,"h":128},"spriteSourceSize":{"x":0,"y":0,"w":128,"h":128}},"PA_1505":{"frame":{"x":512,"y":1920,"w":128,"h":128},"sourceSize":{"w":128,"h":128},"spriteSourceSize":{"x":0,"y":0,"w":128,"h":128}},"PA_1506":{"frame":{"x":640,"y":1920,"w":128,"h":128},"sourceSize":{"w":128,"h":128},"spriteSourceSize":{"x":0,"y":0,"w":128,"h":128}},"PA_1507":{"frame":{"x":768,"y":1920,"w":128,"h":128},"sourceSize":{"w":128,"h":128},"spriteSourceSize":{"x":0,"y":0,"w":128,"h":128}},"PA_1508":{"frame":{"x":896,"y":1920,"w":128,"h":128},"sourceSize":{"w":128,"h":128},"spriteSourceSize":{"x":0,"y":0,"w":128,"h":128}},"PA_1509":{"frame":{"x":1024,"y":1920,"w":128,"h":128},"sourceSize":{"w":128,"h":128},"spriteSourceSize":{"x":0,"y":0,"w":128,"h":128}},"PA_1510":{"frame":{"x":1152,"y":1920,"w":128,"h":128},"sourceSize":{"w":128,"h":128},"spriteSourceSize":{"x":0,"y":0,"w":128,"h":128}},"PA_1511":{"frame":{"x":1280,"y":1920,"w":128,"h":128},"sourceSize":{"w":128,"h":128},"spriteSourceSize":{"x":0,"y":0,"w":128,"h":128}},"PA_1512":{"frame":{"x":1408,"y":1920,"w":128,"h":128},"sourceSize":{"w":128,"h":128},"spriteSourceSize":{"x":0,"y":0,"w":128,"h":128}},"PA_1513":{"frame":{"x":1536,"y":1920,"w":128,"h":128},"sourceSize":{"w":128,"h":128},"spriteSourceSize":{"x":0,"y":0,"w":128,"h":128}},"PA_1514":{"frame":{"x":1664,"y":1920,"w":128,"h":128},"sourceSize":{"w":128,"h":128},"spriteSourceSize":{"x":0,"y":0,"w":128,"h":128}},"PA_1515":{"frame":{"x":1792,"y":1920,"w":128,"h":128},"sourceSize":{"w":128,"h":128},"spriteSourceSize":{"x":0,"y":0,"w":128,"h":128}},"PA_1516":{"frame":{"x":1920,"y":1920,"w":128,"h":128},"sourceSize":{"w":128,"h":128},"spriteSourceSize":{"x":0,"y":0,"w":128,"h":128}},"PA_1517":{"frame":{"x":2048,"y":1920,"w":128,"h":128},"sourceSize":{"w":128,"h":128},"spriteSourceSize":{"x":0,"y":0,"w":128,"h":128}},"PA_1518":{"frame":{"x":2176,"y":1920,"w":128,"h":128},"sourceSize":{"w":128,"h":128},"spriteSourceSize":{"x":0,"y":0,"w":128,"h":128}},"PA_1519":{"frame":{"x":2304,"y":1920,"w":128,"h":128},"sourceSize":{"w":128,"h":128},"spriteSourceSize":{"x":0,"y":0,"w":128,"h":128}},"PA_1520":{"frame":{"x":2432,"y":1920,"w":128,"h":128},"sourceSize":{"w":128,"h":128},"spriteSourceSize":{"x":0,"y":0,"w":128,"h":128}},"PA_1521":{"frame":{"x":0,"y":2048,"w":128,"h":128},"sourceSize":{"w":128,"h":128},"spriteSourceSize":{"x":0,"y":0,"w":128,"h":128}},"PA_1522":{"frame":{"x":128,"y":2048,"w":128,"h":128},"sourceSize":{"w":128,"h":128},"spriteSourceSize":{"x":0,"y":0,"w":128,"h":128}},"PA_1523":{"frame":{"x":256,"y":2048,"w":128,"h":128},"sourceSize":{"w":128,"h":128},"spriteSourceSize":{"x":0,"y":0,"w":128,"h":128}},"PA_1524":{"frame":{"x":384,"y":2048,"w":128,"h":128},"sourceSize":{"w":128,"h":128},"spriteSourceSize":{"x":0,"y":0,"w":128,"h":128}},"PA_1525":{"frame":{"x":512,"y":2048,"w":128,"h":128},"sourceSize":{"w":128,"h":128},"spriteSourceSize":{"x":0,"y":0,"w":128,"h":128}},"PA_1526":{"frame":{"x":640,"y":2048,"w":128,"h":128},"sourceSize":{"w":128,"h":128},"spriteSourceSize":{"x":0,"y":0,"w":128,"h":128}},"PA_1527":{"frame":{"x":768,"y":2048,"w":128,"h":128},"sourceSize":{"w":128,"h":128},"spriteSourceSize":{"x":0,"y":0,"w":128,"h":128}},"PA_1528":{"frame":{"x":896,"y":2048,"w":128,"h":128},"sourceSize":{"w":128,"h":128},"spriteSourceSize":{"x":0,"y":0,"w":128,"h":128}},"PA_1529":{"frame":{"x":1024,"y":2048,"w":128,"h":128},"sourceSize":{"w":128,"h":128},"spriteSourceSize":{"x":0,"y":0,"w":128,"h":128}},"PA_1530":{"frame":{"x":1152,"y":2048,"w":128,"h":128},"sourceSize":{"w":128,"h":128},"spriteSourceSize":{"x":0,"y":0,"w":128,"h":128}},"PA_1531":{"frame":{"x":1280,"y":2048,"w":128,"h":128},"sourceSize":{"w":128,"h":128},"spriteSourceSize":{"x":0,"y":0,"w":128,"h":128}},"PA_1532":{"frame":{"x":1408,"y":2048,"w":128,"h":128},"sourceSize":{"w":128,"h":128},"spriteSourceSize":{"x":0,"y":0,"w":128,"h":128}},"PA_1533":{"frame":{"x":1536,"y":2048,"w":128,"h":128},"sourceSize":{"w":128,"h":128},"spriteSourceSize":{"x":0,"y":0,"w":128,"h":128}},"PA_1534":{"frame":{"x":1664,"y":2048,"w":128,"h":128},"sourceSize":{"w":128,"h":128},"spriteSourceSize":{"x":0,"y":0,"w":128,"h":128}},"PA_1535":{"frame":{"x":1792,"y":2048,"w":128,"h":128},"sourceSize":{"w":128,"h":128},"spriteSourceSize":{"x":0,"y":0,"w":128,"h":128}},"PA_1536":{"frame":{"x":1920,"y":2048,"w":128,"h":128},"sourceSize":{"w":128,"h":128},"spriteSourceSize":{"x":0,"y":0,"w":128,"h":128}},"PA_1537":{"frame":{"x":2048,"y":2048,"w":128,"h":128},"sourceSize":{"w":128,"h":128},"spriteSourceSize":{"x":0,"y":0,"w":128,"h":128}},"PA_1538":{"frame":{"x":2176,"y":2048,"w":128,"h":128},"sourceSize":{"w":128,"h":128},"spriteSourceSize":{"x":0,"y":0,"w":128,"h":128}},"PA_1539":{"frame":{"x":2304,"y":2048,"w":128,"h":128},"sourceSize":{"w":128,"h":128},"spriteSourceSize":{"x":0,"y":0,"w":128,"h":128}},"PA_1540":{"frame":{"x":2432,"y":2048,"w":128,"h":128},"sourceSize":{"w":128,"h":128},"spriteSourceSize":{"x":0,"y":0,"w":128,"h":128}},"PA_1541":{"frame":{"x":0,"y":2176,"w":128,"h":128},"sourceSize":{"w":128,"h":128},"spriteSourceSize":{"x":0,"y":0,"w":128,"h":128}},"PA_1542":{"frame":{"x":128,"y":2176,"w":128,"h":128},"sourceSize":{"w":128,"h":128},"spriteSourceSize":{"x":0,"y":0,"w":128,"h":128}},"PA_1543":{"frame":{"x":256,"y":2176,"w":128,"h":128},"sourceSize":{"w":128,"h":128},"spriteSourceSize":{"x":0,"y":0,"w":128,"h":128}},"PA_1544":{"frame":{"x":384,"y":2176,"w":128,"h":128},"sourceSize":{"w":128,"h":128},"spriteSourceSize":{"x":0,"y":0,"w":128,"h":128}},"PA_1545":{"frame":{"x":512,"y":2176,"w":128,"h":128},"sourceSize":{"w":128,"h":128},"spriteSourceSize":{"x":0,"y":0,"w":128,"h":128}}},"meta":{"app":"PixiJS","version":"5.0.0","image":"PA_03.avif","format":"RGBA8888","size":{"w":2560,"h":2304},"scale":"1"}}